check_rq/__init__.py
check_rq/check_rq.py
check_rq-0.1.5.dist-info/LICENSE
check_rq-0.1.5.dist-info/METADATA
check_rq-0.1.5.dist-info/WHEEL
check_rq-0.1.5.dist-info/entry_points.txt
check_rq-0.1.5.dist-info/top_level.txt
check_rq-0.1.5.dist-info/RECORD
