Metadata-Version: 2.1
Name: check-rq
Version: 0.1.5
Summary: Icinga/Nagios check for RQ (Redis Queue)
Home-page: https://github.com/crafterwerkbon/check_rq
Author: Crafter B.V.
Author-email: koen@getcrafter.com
License: MIT
Project-URL: Source, https://github.com/crafterwerkbon/check_rq
Platform: UNKNOWN
Classifier: License :: OSI Approved :: MIT License
Classifier: Programming Language :: Python :: 3
Requires-Python: >=3.5
Requires-Dist: nagiosplugin
Requires-Dist: rq
